jupyterlab_requirements/__init__.py
jupyterlab_requirements/cli.py
jupyterlab_requirements/dependency_management/__init__.py
jupyterlab_requirements/dependency_management/api.py
jupyterlab_requirements/dependency_management/base.py
jupyterlab_requirements/dependency_management/dependencies_files_handler.py
jupyterlab_requirements/dependency_management/dependencies_stored_handler.py
jupyterlab_requirements/dependency_management/discover_handler.py
jupyterlab_requirements/dependency_management/install_handler.py
jupyterlab_requirements/dependency_management/kernel_handler.py
jupyterlab_requirements/dependency_management/lib.py
jupyterlab_requirements/dependency_management/magic_commands.py
jupyterlab_requirements/dependency_management/pipenv.py
jupyterlab_requirements/dependency_management/thoth.py
jupyterlab_requirements/dependency_management/thoth_config_handler.py
jupyterlab_requirements/dependency_management/thoth_invectio.py
jupyterlab_requirements/labextension/package.json
jupyterlab_requirements/labextension/static/249.63a6754cf57ca7c07536.js
jupyterlab_requirements/labextension/static/549.2f5402299055844264cc.js
jupyterlab_requirements/labextension/static/666.bd47fae45deda8ef75fd.js
jupyterlab_requirements/labextension/static/666.bd47fae45deda8ef75fd.js.LICENSE.txt
jupyterlab_requirements/labextension/static/669.824a23027295ca83e618.js
jupyterlab_requirements/labextension/static/697.6ddaa3b02246bfbeaca6.js
jupyterlab_requirements/labextension/static/80.a80b3012898cbbbe2a3f.js
jupyterlab_requirements/labextension/static/80.a80b3012898cbbbe2a3f.js.LICENSE.txt
jupyterlab_requirements/labextension/static/801.f26b1bfc59d124034b99.js
jupyterlab_requirements/labextension/static/remoteEntry.c9056ae0ba62edc54de6.js
jupyterlab_requirements/labextension/static/style.js
jupyterlab_requirements/labextension/static/third-party-licenses.json
jupyterlab_requirements-0.16.2.data/data/etc/jupyter/jupyter_notebook_config.d/jupyterlab_requirements.json
jupyterlab_requirements-0.16.2.dist-info/LICENSE
jupyterlab_requirements-0.16.2.dist-info/METADATA
jupyterlab_requirements-0.16.2.dist-info/WHEEL
jupyterlab_requirements-0.16.2.dist-info/entry_points.txt
jupyterlab_requirements-0.16.2.dist-info/top_level.txt
jupyterlab_requirements-0.16.2.dist-info/RECORD
