Metadata-Version: 2.1
Name: jupyterlab-requirements
Version: 0.16.2
Summary: JupyterLab Extension for dependency management and optimization
Home-page: https://github.com/thoth-station/jupyterlab-requirements
Author: Francesco Murdaca
Author-email: fmurdaca@redhat.com
License: GPLv3+
Project-URL: Documentation, https://github.com/thoth-station/jupyterlab-requirements/blob/master/README.md
Project-URL: Source Code, https://github.com/thoth-station/jupyterlab-requirements/
Project-URL: Issues, https://github.com/thoth-station/jupyterlab-requirements/issues
Project-URL: Changelog, https://github.com/thoth-station/jupyterlab-requirements/blob/master/CHANGELOG.md
Keywords: Jupyter,JupyterLab
Platform: Linux
Platform: Mac OS X
Platform: Windows
Classifier: Programming Language :: Python
Classifier: Programming Language :: Python :: 3
Classifier: Programming Language :: Python :: 3.8
Classifier: Framework :: IPython
Classifier: Framework :: Jupyter
Classifier: Natural Language :: English
Classifier: Operating System :: OS Independent
Requires-Python: >=3.8
License-File: LICENSE
Requires-Dist: click
Requires-Dist: invectio
Requires-Dist: ipynbname
Requires-Dist: ipykernel
Requires-Dist: ipython
Requires-Dist: jupyterlab (<4,>=3.1.0)
Requires-Dist: jupyter-require (>=0.4.0)
Requires-Dist: pyyaml
Requires-Dist: rich
Requires-Dist: thamos (>=1.21.0)
Requires-Dist: thoth-common
Requires-Dist: thoth-python (>=0.16.6)
Requires-Dist: virtualenv
Requires-Dist: voluptuous
